pybnf/__init__.py
pybnf/__main__.py
pybnf/algorithms.py
pybnf/cluster.py
pybnf/config.py
pybnf/constraint.py
pybnf/data.py
pybnf/juliaMod.py
pybnf/objective.py
pybnf/parse.py
pybnf/printing.py
pybnf/pset.py
pybnf/pybnf.py
pybnf1.2.1-1.2.0.dist-info/LICENSE
pybnf1.2.1-1.2.0.dist-info/METADATA
pybnf1.2.1-1.2.0.dist-info/WHEEL
pybnf1.2.1-1.2.0.dist-info/entry_points.txt
pybnf1.2.1-1.2.0.dist-info/top_level.txt
pybnf1.2.1-1.2.0.dist-info/RECORD
