Metadata-Version: 2.1
Name: pybnf1.2.1
Version: 1.2.0
Summary: An application for parallel fitting of BioNetGen and SBML models using metaheuristics
Author: Eshan Mitra, Ryan Suderman, Alex Ionkov
Requires-Python: >=3.5
License-File: LICENSE
Requires-Dist: distributed (>=2021.6.2)
Requires-Dist: paramiko
Requires-Dist: msgpack (==0.6.2)
Requires-Dist: numpy
Requires-Dist: nose
Requires-Dist: pyparsing
Requires-Dist: libroadrunner (>=1.5.2)
Requires-Dist: dask (>=2021.5.0)
Requires-Dist: tornado (>=6.1)
Requires-Dist: scipy
